arn/__init__.py
arn/ecs.py
arn/elbv2.py
arn/iam.py
arn/s3.py
arn-0.1.5.dist-info/LICENSE
arn-0.1.5.dist-info/METADATA
arn-0.1.5.dist-info/WHEEL
arn-0.1.5.dist-info/top_level.txt
arn-0.1.5.dist-info/RECORD
