Metadata-Version: 2.1
Name: arn
Version: 0.1.5
Summary: A Python library for parsing AWS ARNs
Home-page: UNKNOWN
License: UNKNOWN
Platform: UNKNOWN
Requires-Python: >=3.6
Requires-Dist: dataclasses ; python_version < "3.7"
Provides-Extra: dev
Requires-Dist: black (==19.3b0) ; extra == 'dev'
Requires-Dist: flake8 (==3.7.8) ; extra == 'dev'
Requires-Dist: invoke (==1.3.0) ; extra == 'dev'
Requires-Dist: isort (==4.3.21) ; extra == 'dev'
Requires-Dist: pytest (==5.2.1) ; extra == 'dev'
Requires-Dist: pytest-cov (==2.8.1) ; extra == 'dev'
Requires-Dist: pytest-watch (==4.2.0) ; extra == 'dev'
Requires-Dist: twine (==2.0.0) ; extra == 'dev'
Requires-Dist: wheel (==0.34.2) ; extra == 'dev'
